{"1522605849":{"main_st":null,"from_st":null,"to_st":null,"sos":null,"error":null,"geom":{"type":"LineString","coordinates":[[-73.858031,40.856506],[-73.858176,40.856816]]},"length":"120","uncoded_spaces":"6","uncoded_ft":"119.88328231560253","parking_lanes":2,"signs":[]},"1522605850":{"main_st":null,"from_st":null,"to_st":null,"sos":null,"error":null,"geom":{"type":"LineString","coordinates":[[-73.859086,40.856807],[-73.858195,40.856827]]},"length":"247","uncoded_spaces":"13","uncoded_ft":"246.74436809555093","parking_lanes":2,"signs":[]},"1522605851":{"main_st":null,"from_st":null,"to_st":null,"sos":null,"error":null,"geom":{"type":"LineString","coordinates":[[-73.85865,40.855954],[-73.859074,40.856823]]},"length":"338","uncoded_spaces":"18","uncoded_ft":"337.68329770910356","parking_lanes":2,"signs":[]},"1522611678":{"main_st":null,"from_st":null,"to_st":null,"sos":null,"error":null,"geom":{"type":"LineString","coordinates":[[-73.858675,40.855968],[-73.858051,40.85647]]},"length":"251","uncoded_spaces":"13","uncoded_ft":"251.35979584970303","parking_lanes":2,"signs":[]},"S-01415248":{"main_st":"ESPLANADE*W RDWY","from_st":"HAIGHT AVENUE","to_st":"LURTING AVENUE","sos":"E","error":"{\"error_code\": \"EE\", \"error_message\": \"'ESPLANADE*W RDWY' NOT RECOGNIZED. IS IT 'ESPLANADE'?                           \"}","geom":{"type":"LineString","coordinates":[[-73.858596,40.855912],[-73.857972,40.856413]]},"length":"251","uncoded_spaces":null,"uncoded_ft":null,"parking_lanes":2,"signs":[{"seq":"1","distx":"0","arrow":"NULL","mutcd_code":"CL","geom":{"type":"Point","coordinates":[-73.857972,40.856413]}},{"seq":"2","distx":"78","arrow":"NULL","mutcd_code":"PS-28B","geom":{"type":"Point","coordinates":[-73.858166,40.856258]}},{"seq":"3","distx":"170","arrow":"NULL","mutcd_code":"PS-28B","geom":{"type":"Point","coordinates":[-73.858394,40.856074]}},{"seq":"4","distx":"249","arrow":"NULL","mutcd_code":"CL","geom":{"type":"Point","coordinates":[-73.85859,40.855917]}}],"parking_length":{"2":{"evening rush":{"":249},"night":{"":249},"morning rush":{"":249},"daytime":{"":249},"evening":{"":249}},"5":{"evening rush":{"":249},"daytime":{"":249},"night":{"":249},"morning rush":{"":249},"evening":{"":249}},"3":{"morning rush":{"":249},"night":{"":249},"evening rush":{"":249},"evening":{"":249},"daytime":{"":249}},"0":{"daytime":{"":249},"evening":{"":249},"night":{"":249},"morning rush":{"":249},"evening rush":{"":249}},"6":{"daytime":{"":249},"evening":{"":249},"evening rush":{"":249},"morning rush":{"":249},"night":{"":249}},"1":{"evening rush":{"":249},"daytime":{"":249},"evening":{"":249},"night":{"":249},"morning rush":{"P":249}},"4":{"morning rush":{"":249},"evening":{"":249},"daytime":{"":249},"night":{"":249},"evening rush":{"":249}}},"parking_spaces":{"2":{"evening rush":{"":13},"night":{"":13},"morning rush":{"":13},"daytime":{"":13},"evening":{"":13}},"5":{"evening rush":{"":13},"daytime":{"":13},"night":{"":13},"morning rush":{"":13},"evening":{"":13}},"3":{"morning rush":{"":13},"night":{"":13},"evening rush":{"":13},"evening":{"":13},"daytime":{"":13}},"0":{"daytime":{"":13},"evening":{"":13},"night":{"":13},"morning rush":{"":13},"evening rush":{"":13}},"6":{"daytime":{"":13},"evening":{"":13},"evening rush":{"":13},"morning rush":{"":13},"night":{"":13}},"1":{"evening rush":{"":13},"daytime":{"":13},"evening":{"":13},"night":{"":13},"morning rush":{"P":13}},"4":{"morning rush":{"":13},"evening":{"":13},"daytime":{"":13},"night":{"":13},"evening rush":{"":13}}}},"S-01415296":{"main_st":"ESPLANADE*E RDWY","from_st":"LURTING AVENUE","to_st":"HAIGHT AVENUE","sos":"W","error":"{\"error_code\": \"EE\", \"error_message\": \"'ESPLANADE*E RDWY' NOT RECOGNIZED. IS IT 'ESPLANADE'?                           \"}","geom":null,"length":null,"uncoded_spaces":null,"uncoded_ft":null,"parking_lanes":null,"signs":[{"seq":"1","distx":"0","arrow":"NULL","mutcd_code":"CL","geom":null},{"seq":"2","distx":"68","arrow":"NULL","mutcd_code":"PS-31B","geom":null},{"seq":"3","distx":"162","arrow":"NULL","mutcd_code":"PS-31B","geom":null},{"seq":"4","distx":"246","arrow":"NULL","mutcd_code":"CL","geom":null}],"parking_length":{"5":{"evening":{"":246},"evening rush":{"":246},"morning rush":{"":246},"night":{"":246},"daytime":{"":246}},"6":{"night":{"":246},"evening rush":{"":246},"morning rush":{"":246},"daytime":{"":246},"evening":{"":246}},"1":{"morning rush":{"":246},"evening rush":{"":246},"daytime":{"":246},"night":{"":246},"evening":{"":246}},"3":{"evening rush":{"":246},"daytime":{"":246},"evening":{"":246},"morning rush":{"":246},"night":{"":246}},"0":{"evening":{"":246},"evening rush":{"":246},"night":{"":246},"daytime":{"":246},"morning rush":{"":246}},"2":{"daytime":{"":246},"evening rush":{"":246},"night":{"":246},"evening":{"":246},"morning rush":{"":246}},"4":{"evening rush":{"":246},"morning rush":{"P":246},"daytime":{"":246},"evening":{"":246},"night":{"":246}}},"parking_spaces":{"5":{"evening":{"":13},"evening rush":{"":13},"morning rush":{"":13},"night":{"":13},"daytime":{"":13}},"6":{"night":{"":13},"evening rush":{"":13},"morning rush":{"":13},"daytime":{"":13},"evening":{"":13}},"1":{"morning rush":{"":13},"evening rush":{"":13},"daytime":{"":13},"night":{"":13},"evening":{"":13}},"3":{"evening rush":{"":13},"daytime":{"":13},"evening":{"":13},"morning rush":{"":13},"night":{"":13}},"0":{"evening":{"":13},"evening rush":{"":13},"night":{"":13},"daytime":{"":13},"morning rush":{"":13}},"2":{"daytime":{"":13},"evening rush":{"":13},"night":{"":13},"evening":{"":13},"morning rush":{"":13}},"4":{"evening rush":{"":13},"morning rush":{"P":13},"daytime":{"":13},"evening":{"":13},"night":{"":13}}}},"S-284213":{"main_st":"LURTING AVENUE","from_st":"PELHAM PARKWAY SOUTH","to_st":"ESPLANADE AVENUE","sos":"E","error":null,"geom":null,"length":null,"uncoded_spaces":null,"uncoded_ft":null,"parking_lanes":null,"signs":[{"seq":"1","distx":"0","arrow":"NULL","mutcd_code":"CL","geom":null},{"seq":"2","distx":"15","arrow":"NULL","mutcd_code":"PL","geom":null},{"seq":"3","distx":"44","arrow":"N","mutcd_code":"SP-10BA","geom":null},{"seq":"4","distx":"108","arrow":"S","mutcd_code":"R7-40RA","geom":null},{"seq":"5","distx":"142","arrow":"N","mutcd_code":"R7-40RA","geom":null},{"seq":"6","distx":"309","arrow":"NULL","mutcd_code":"PL","geom":null},{"seq":"7","distx":"327","arrow":"NULL","mutcd_code":"CL","geom":null}],"parking_length":{"4":{"daytime":{"P":98,"S":29},"night":{"P":98,"S":29},"evening":{"S":29,"P":98},"morning rush":{"P":98,"S":29},"evening rush":{"P":98,"S":29}},"3":{"evening rush":{"S":29,"P":98},"evening":{"P":98,"S":29},"night":{"P":98,"S":29},"morning rush":{"P":98,"S":29},"daytime":{"P":98,"S":29}},"1":{"night":{"S":29,"P":98},"evening rush":{"P":98,"S":29},"daytime":{"P":98,"S":29},"evening":{"S":29,"P":98},"morning rush":{"S":29,"P":98}},"5":{"night":{"P":98,"S":29},"evening":{"P":98,"S":29},"daytime":{"S":29,"P":98},"evening rush":{"S":29,"P":98},"morning rush":{"P":98,"S":29}},"2":{"night":{"S":29,"P":98},"morning rush":{"S":29,"P":98},"evening":{"S":29,"P":98},"evening rush":{"P":98,"S":29},"daytime":{"S":29,"P":98}},"0":{"evening":{"S":29,"P":98},"daytime":{"P":98,"S":29},"night":{"P":98,"S":29},"morning rush":{"S":29,"P":98},"evening rush":{"P":98,"S":29}},"6":{"morning rush":{"P":98,"S":29},"night":{"P":98,"S":29},"evening":{"S":29,"P":98},"daytime":{"P":98,"S":29},"evening rush":{"S":29,"P":98}}},"parking_spaces":{"4":{"daytime":{"P":4,"S":1},"night":{"P":4,"S":1},"evening":{"S":1,"P":4},"morning rush":{"P":4,"S":1},"evening rush":{"P":4,"S":1}},"3":{"evening rush":{"S":1,"P":4},"evening":{"P":4,"S":1},"night":{"P":4,"S":1},"morning rush":{"P":4,"S":1},"daytime":{"P":4,"S":1}},"1":{"night":{"S":1,"P":4},"evening rush":{"P":4,"S":1},"daytime":{"P":4,"S":1},"evening":{"S":1,"P":4},"morning rush":{"S":1,"P":4}},"5":{"night":{"P":4,"S":1},"evening":{"P":4,"S":1},"daytime":{"S":1,"P":4},"evening rush":{"S":1,"P":4},"morning rush":{"P":4,"S":1}},"2":{"night":{"S":1,"P":4},"morning rush":{"S":1,"P":4},"evening":{"S":1,"P":4},"evening rush":{"P":4,"S":1},"daytime":{"S":1,"P":4}},"0":{"evening":{"S":1,"P":4},"daytime":{"P":4,"S":1},"night":{"P":4,"S":1},"morning rush":{"S":1,"P":4},"evening rush":{"P":4,"S":1}},"6":{"morning rush":{"P":4,"S":1},"night":{"P":4,"S":1},"evening":{"S":1,"P":4},"daytime":{"P":4,"S":1},"evening rush":{"S":1,"P":4}}}}}