{"S-01456599":{"signs":[{"seq":"1","distx":"0","arrow":null,"mutcd_code":"CL","type":null,"days":null,"start_time":null,"end_time":null,"arrow_type":null,"extra":"Curb Line","checked":null},{"seq":"2","distx":"8","arrow":null,"mutcd_code":"PL","type":null,"days":null,"start_time":null,"end_time":null,"arrow_type":null,"extra":"Property Line","checked":null},{"seq":"3","distx":"126","arrow":"S","mutcd_code":"SP-477BA","type":"S","days":null,"start_time":null,"end_time":null,"arrow_type":"-->","extra":"BUS STOP SIGN (BUS & HANDICAP SYMBOLS) ","checked":null},{"seq":"4","distx":"126","arrow":null,"mutcd_code":"SI-1878G","type":null,"days":null,"start_time":null,"end_time":null,"arrow_type":null,"extra":"LOCAL MTA BUS ROUTE PANEL (TEXT TO BE MODIFIED AS REQUESTED)","checked":null},{"seq":"5","distx":"126","arrow":null,"mutcd_code":"SI-1879G","type":null,"days":null,"start_time":null,"end_time":null,"arrow_type":null,"extra":"LOCAL MTA BUS DESTINATION PANEL (TEXT TO BE MODIFIED AS REQUIRED)","checked":null},{"seq":"6","distx":"126","arrow":null,"mutcd_code":"SI-584G","type":null,"days":null,"start_time":null,"end_time":null,"arrow_type":null,"extra":"14 STREET & UNION SQ (BOTTOM LOCATION PANEL)","checked":null},{"seq":"7","distx":"155","arrow":null,"mutcd_code":"PS-31B","type":"P","days":"F","start_time":"08:30:00","end_time":"10:00:00","arrow_type":"<->","extra":null,"checked":false},{"seq":"8","distx":"234","arrow":null,"mutcd_code":"PS-31B","type":"P","days":"F","start_time":"08:30:00","end_time":"10:00:00","arrow_type":"<->","extra":null,"checked":false},{"seq":"9","distx":"383","arrow":null,"mutcd_code":"PS-31B","type":"P","days":"F","start_time":"08:30:00","end_time":"10:00:00","arrow_type":"<->","extra":null,"checked":false},{"seq":"10","distx":"527","arrow":null,"mutcd_code":"PS-31B","type":"P","days":"F","start_time":"08:30:00","end_time":"10:00:00","arrow_type":"<->","extra":null,"checked":false},{"seq":"11","distx":"664","arrow":null,"mutcd_code":"PS-31B","type":"P","days":"F","start_time":"08:30:00","end_time":"10:00:00","arrow_type":"<->","extra":null,"checked":false},{"seq":"12","distx":"730","arrow":null,"mutcd_code":"PL","type":null,"days":null,"start_time":null,"end_time":null,"arrow_type":null,"extra":"Property Line","checked":null},{"seq":"13","distx":"740","arrow":null,"mutcd_code":"CL","type":null,"days":null,"start_time":null,"end_time":null,"arrow_type":null,"extra":"Curb Line","checked":null}],"geom":{"type":"MultiLineString","coordinates":[[[-73.898746,40.642059],[-73.898057,40.64144]],[[-73.898057,40.64144],[-73.898057,40.64144]],[[-73.898057,40.64144],[-73.898057,40.64144]],[[-73.898057,40.64144],[-73.896929,40.640428]]]},"main_st":"ROCKAWAY PARKWAY","from_st":"AVENUE K","to_st":"AVENUE J","sos":"E","parking":[],"parking_length":[{"daytime":{"":722},"evening":{"":722},"evening rush":{"":722},"morning rush":{"":722},"night":{"":722}},{"daytime":{"":722},"evening":{"":722},"evening rush":{"":722},"morning rush":{"":722},"night":{"":722}},{"daytime":{"":722},"evening":{"":722},"evening rush":{"":722},"morning rush":{"":722},"night":{"":722}},{"daytime":{"":722},"evening":{"":722},"evening rush":{"":722},"morning rush":{"":722},"night":{"":722}},{"daytime":{"":722},"evening":{"":722},"evening rush":{"":722},"morning rush":{"P":722},"night":{"":722}},{"daytime":{"":722},"evening":{"":722},"evening rush":{"":722},"morning rush":{"":722},"night":{"":722}},{"daytime":{"":722},"evening":{"":722},"evening rush":{"":722},"morning rush":{"":722},"night":{"":722}}],"parking_spaces":[{"daytime":{"":40},"evening":{"":40},"evening rush":{"":40},"morning rush":{"":40},"night":{"":40}},{"daytime":{"":40},"evening":{"":40},"evening rush":{"":40},"morning rush":{"":40},"night":{"":40}},{"daytime":{"":40},"evening":{"":40},"evening rush":{"":40},"morning rush":{"":40},"night":{"":40}},{"daytime":{"":40},"evening":{"":40},"evening rush":{"":40},"morning rush":{"":40},"night":{"":40}},{"daytime":{"":40},"evening":{"":40},"evening rush":{"":40},"morning rush":{"P":40},"night":{"":40}},{"daytime":{"":40},"evening":{"":40},"evening rush":{"":40},"morning rush":{"":40},"night":{"":40}},{"daytime":{"":40},"evening":{"":40},"evening rush":{"":40},"morning rush":{"":40},"night":{"":40}}]},"S-119538":{"signs":[{"seq":"1","distx":"0","arrow":null,"mutcd_code":"CL","type":null,"days":null,"start_time":null,"end_time":null,"arrow_type":null,"extra":"Curb Line","checked":null},{"seq":"2","distx":"10","arrow":null,"mutcd_code":"PL","type":null,"days":null,"start_time":null,"end_time":null,"arrow_type":null,"extra":"Property Line","checked":null},{"seq":"5","distx":"257","arrow":null,"mutcd_code":"PL","type":null,"days":null,"start_time":null,"end_time":null,"arrow_type":null,"extra":"Property Line","checked":null},{"seq":"6","distx":"267","arrow":null,"mutcd_code":"CL","type":null,"days":null,"start_time":null,"end_time":null,"arrow_type":null,"extra":"Curb Line","checked":null}],"geom":{"type":"LineString","coordinates":[[-73.897063,40.640421],[-73.896182,40.640987]]},"main_st":"AVENUE K","from_st":"EAST   98 STREET","to_st":"ROCKAWAY PARKWAY","sos":"N","parking":[],"parking_length":[{"daytime":{"":247},"evening":{"":247},"evening rush":{"":247},"morning rush":{"":247},"night":{"":247}},{"daytime":{"":247},"evening":{"":247},"evening rush":{"":247},"morning rush":{"":247},"night":{"":247}},{"daytime":{"":247},"evening":{"":247},"evening rush":{"":247},"morning rush":{"P":247},"night":{"":247}},{"daytime":{"":247},"evening":{"":247},"evening rush":{"":247},"morning rush":{"":247},"night":{"":247}},{"daytime":{"":247},"evening":{"":247},"evening rush":{"":247},"morning rush":{"":247},"night":{"":247}},{"daytime":{"":247},"evening":{"":247},"evening rush":{"":247},"morning rush":{"":247},"night":{"":247}},{"daytime":{"":247},"evening":{"":247},"evening rush":{"":247},"morning rush":{"":247},"night":{"":247}}],"parking_spaces":[{"daytime":{"":13},"evening":{"":13},"evening rush":{"":13},"morning rush":{"":13},"night":{"":13}},{"daytime":{"":13},"evening":{"":13},"evening rush":{"":13},"morning rush":{"":13},"night":{"":13}},{"daytime":{"":13},"evening":{"":13},"evening rush":{"":13},"morning rush":{"P":13},"night":{"":13}},{"daytime":{"":13},"evening":{"":13},"evening rush":{"":13},"morning rush":{"":13},"night":{"":13}},{"daytime":{"":13},"evening":{"":13},"evening rush":{"":13},"morning rush":{"":13},"night":{"":13}},{"daytime":{"":13},"evening":{"":13},"evening rush":{"":13},"morning rush":{"":13},"night":{"":13}},{"daytime":{"":13},"evening":{"":13},"evening rush":{"":13},"morning rush":{"":13},"night":{"":13}}]},"S-391839":{"signs":[{"seq":"1","distx":"0","arrow":null,"mutcd_code":"CL","type":null,"days":null,"start_time":null,"end_time":null,"arrow_type":null,"extra":"Curb Line","checked":null},{"seq":"2","distx":"19","arrow":null,"mutcd_code":"PL","type":null,"days":null,"start_time":null,"end_time":null,"arrow_type":null,"extra":"Property Line","checked":null},{"seq":"3","distx":"35","arrow":"W","mutcd_code":"PS-1GA","type":"S","days":"A","start_time":"00:00:00","end_time":"00:00:00","arrow_type":"-->","extra":null,"checked":false},{"seq":"4","distx":"35","arrow":"E","mutcd_code":"PS-29BA","type":"P","days":"W","start_time":"08:30:00","end_time":"10:00:00","arrow_type":"-->","extra":null,"checked":false},{"seq":"5","distx":"208","arrow":null,"mutcd_code":"PS-29B","type":"P","days":"W","start_time":"08:30:00","end_time":"10:00:00","arrow_type":"<->","extra":null,"checked":false},{"seq":"6","distx":"259","arrow":null,"mutcd_code":"PL","type":null,"days":null,"start_time":null,"end_time":null,"arrow_type":null,"extra":"Property Line","checked":null},{"seq":"7","distx":"268","arrow":null,"mutcd_code":"CL","type":null,"days":null,"start_time":null,"end_time":null,"arrow_type":null,"extra":"Curb Line","checked":null}],"geom":{"type":"MultiLineString","coordinates":[[[-73.898231,40.642312],[-73.898777,40.641959]],[[-73.897898,40.642527],[-73.898231,40.642312]]]},"main_st":"AVENUE J","from_st":"ROCKAWAY PARKWAY","to_st":"EAST   98 STREET","sos":"S","parking":[],"parking_length":[{"daytime":{"S":16,"":224},"evening":{"S":16,"":224},"evening rush":{"S":16,"":224},"morning rush":{"S":16,"":224},"night":{"S":16,"":224}},{"daytime":{"S":16,"":224},"evening":{"S":16,"":224},"evening rush":{"S":16,"":224},"morning rush":{"S":16,"":224},"night":{"S":16,"":224}},{"daytime":{"S":16,"":224},"evening":{"S":16,"":224},"evening rush":{"S":16,"":224},"morning rush":{"P":224,"S":16},"night":{"S":16,"":224}},{"daytime":{"S":16,"":224},"evening":{"S":16,"":224},"evening rush":{"S":16,"":224},"morning rush":{"S":16,"":224},"night":{"S":16,"":224}},{"daytime":{"S":16,"":224},"evening":{"S":16,"":224},"evening rush":{"S":16,"":224},"morning rush":{"S":16,"":224},"night":{"S":16,"":224}},{"daytime":{"S":16,"":224},"evening":{"S":16,"":224},"evening rush":{"S":16,"":224},"morning rush":{"S":16,"":224},"night":{"S":16,"":224}},{"daytime":{"S":16,"":224},"evening":{"S":16,"":224},"evening rush":{"S":16,"":224},"morning rush":{"S":16,"":224},"night":{"S":16,"":224}}],"parking_spaces":[{"daytime":{"S":0,"":12},"evening":{"S":0,"":12},"evening rush":{"S":0,"":12},"morning rush":{"S":0,"":12},"night":{"S":0,"":12}},{"daytime":{"S":0,"":12},"evening":{"S":0,"":12},"evening rush":{"S":0,"":12},"morning rush":{"S":0,"":12},"night":{"S":0,"":12}},{"daytime":{"S":0,"":12},"evening":{"S":0,"":12},"evening rush":{"S":0,"":12},"morning rush":{"P":12,"S":0},"night":{"S":0,"":12}},{"daytime":{"S":0,"":12},"evening":{"S":0,"":12},"evening rush":{"S":0,"":12},"morning rush":{"S":0,"":12},"night":{"S":0,"":12}},{"daytime":{"S":0,"":12},"evening":{"S":0,"":12},"evening rush":{"S":0,"":12},"morning rush":{"S":0,"":12},"night":{"S":0,"":12}},{"daytime":{"S":0,"":12},"evening":{"S":0,"":12},"evening rush":{"S":0,"":12},"morning rush":{"S":0,"":12},"night":{"S":0,"":12}},{"daytime":{"S":0,"":12},"evening":{"S":0,"":12},"evening rush":{"S":0,"":12},"morning rush":{"S":0,"":12},"night":{"S":0,"":12}}]},"":{"signs":[],"geom":{"type":"MultiLineString","coordinates":[[[-73.896693,40.641353],[-73.89801,40.642534]],[[-73.897388,40.640924],[-73.896693,40.641353]],[[-73.89667,40.641332],[-73.897366,40.640902]],[[-73.89668,40.641341],[-73.896693,40.641353]],[[-73.896693,40.641353],[-73.896631,40.641391]],[[-73.89668,40.641341],[-73.89668,40.641341]],[[-73.89668,40.641341],[-73.89668,40.641341]],[[-73.89667,40.641332],[-73.89668,40.641341]],[[-73.896608,40.64137],[-73.89667,40.641332]],[[-73.896191,40.640902],[-73.89667,40.641332]]]},"main_st":null,"from_st":null,"to_st":null,"sos":null,"parking":[]}}